{
    "required": true,
    "minVersion": "0.8",
    "package": "com.mcsow.mixin",
    "compatibilityLevel": "JAVA_17",
    "mixins": [
        "PlayerEntityMixin",
        "ServerPlayNetworkHandlerMixin",
        "LivingEntityFallMixin"
    ],
    "client": [
        "ClientPlayerMixin",
        "ClientPlayerEntityTravelMixin",
        "DrawContextAccessor",
        "InGameHudCrosshairMixin",
        "BarExperienceLevelMixin",
        "AbstractClientPlayerFovMixin"
    ],
    "injectors": {
        "defaultRequire": 1
    }
}
